jenkins-stubs/METADATA.toml
jenkins-stubs/__init__.pyi
jenkins-stubs/plugins.pyi
jenkins-stubs/py.typed
jenkins-stubs/version.pyi
types_python_jenkins-1.8.3.20250805.dist-info/licenses/LICENSE
types_python_jenkins-1.8.3.20250805.dist-info/METADATA
types_python_jenkins-1.8.3.20250805.dist-info/WHEEL
types_python_jenkins-1.8.3.20250805.dist-info/top_level.txt
types_python_jenkins-1.8.3.20250805.dist-info/RECORD
